{"ID_Frame": 390, "thingId": "digitaltwin:Laboratorio_Corridoio:1", "People": [{"personID": 0, "skeleton": [{"confidence": 0.0, "pointID": 0, "w_rotation": 1.0, "x": 0.0, "x_rotation": 0.0, "y": 0.0, "y_rotation": 0.0, "z": 0.0, "z_rotation": 0.0}, {"confidence": 0.20233799517154694, "pointID": 1, "w_rotation": 1.0, "x": -28.349000930786133, "x_rotation": 0.0, "y": 1.251731514930725, "y_rotation": 0.0, "z": -1.0849273204803467, "z_rotation": 0.0}, {"confidence": 0.4456849992275238, "pointID": 2, "w_rotation": 1.0, "x": -28.48699951171875, "x_rotation": 0.0, "y": 1.306675910949707, "y_rotation": 0.0, "z": -0.9780666828155518, "z_rotation": 0.0}, {"confidence": 0.34992700815200806, "pointID": 3, "w_rotation": 1.0, "x": -28.565000534057617, "x_rotation": 0.0, "y": 1.0409016609191895, "y_rotation": 0.0, "z": -0.9610025882720947, "z_rotation": 0.0}, {"confidence": 0.20304100215435028, "pointID": 4, "w_rotation": 1.0, "x": -28.46500015258789, "x_rotation": 0.0, "y": 0.8871513605117798, "y_rotation": 0.0, "z": -0.9627807140350342, "z_rotation": 0.0}, {"confidence": 0.0, "pointID": 5, "w_rotation": 1.0, "x": 0.0, "x_rotation": 0.0, "y": 0.0, "y_rotation": 0.0, "z": 0.0, "z_rotation": 0.0}, {"confidence": 0.0, "pointID": 6, "w_rotation": 1.0, "x": 0.0, "x_rotation": 0.0, "y": 0.0, "y_rotation": 0.0, "z": 0.0, "z_rotation": 0.0}, {"confidence": 0.0, "pointID": 7, "w_rotation": 1.0, "x": 0.0, "x_rotation": 0.0, "y": 0.0, "y_rotation": 0.0, "z": 0.0, "z_rotation": 0.0}, {"confidence": 0.26781800389289856, "pointID": 8, "w_rotation": 1.0, "x": -28.316999435424805, "x_rotation": 0.0, "y": 0.7930821180343628, "y_rotation": 0.0, "z": -1.0887830257415771, "z_rotation": 0.0}, {"confidence": 0.1790349930524826, "pointID": 9, "w_rotation": 1.0, "x": -28.304000854492188, "x_rotation": 0.0, "y": 0.7778403759002686, "y_rotation": 0.0, "z": -1.1613714694976807, "z_rotation": 0.0}, {"confidence": 0.06978750228881836, "pointID": 10, "w_rotation": 1.0, "x": -28.39900016784668, "x_rotation": 0.0, "y": 0.44733497500419617, "y_rotation": 0.0, "z": -1.2296557426452637, "z_rotation": 0.0}, {"confidence": 0.0, "pointID": 11, "w_rotation": 1.0, "x": 0.0, "x_rotation": 0.0, "y": 0.0, "y_rotation": 0.0, "z": 0.0, "z_rotation": 0.0}, {"confidence": 0.3084830045700073, "pointID": 12, "w_rotation": 1.0, "x": -28.354000091552734, "x_rotation": 0.0, "y": 0.8027068376541138, "y_rotation": 0.0, "z": -1.017216444015503, "z_rotation": 0.0}, {"confidence": 0.09523239731788635, "pointID": 13, "w_rotation": 1.0, "x": -28.31100082397461, "x_rotation": 0.0, "y": 0.4856298863887787, "y_rotation": 0.0, "z": -0.99129319190979, "z_rotation": 0.0}, {"confidence": 0.0, "pointID": 14, "w_rotation": 1.0, "x": 0.0, "x_rotation": 0.0, "y": 0.0, "y_rotation": 0.0, "z": 0.0, "z_rotation": 0.0}, {"confidence": 0.0, "pointID": 15, "w_rotation": 1.0, "x": 0.0, "x_rotation": 0.0, "y": 0.0, "y_rotation": 0.0, "z": 0.0, "z_rotation": 0.0}, {"confidence": 0.0, "pointID": 16, "w_rotation": 1.0, "x": 0.0, "x_rotation": 0.0, "y": 0.0, "y_rotation": 0.0, "z": 0.0, "z_rotation": 0.0}, {"confidence": 0.0, "pointID": 17, "w_rotation": 1.0, "x": 0.0, "x_rotation": 0.0, "y": 0.0, "y_rotation": 0.0, "z": 0.0, "z_rotation": 0.0}, {"confidence": 0.0, "pointID": 18, "w_rotation": 1.0, "x": 0.0, "x_rotation": 0.0, "y": 0.0, "y_rotation": 0.0, "z": 0.0, "z_rotation": 0.0}, {"confidence": 0.0, "pointID": 19, "w_rotation": 1.0, "x": 0.0, "x_rotation": 0.0, "y": 0.0, "y_rotation": 0.0, "z": 0.0, "z_rotation": 0.0}, {"confidence": 0.0, "pointID": 20, "w_rotation": 1.0, "x": 0.0, "x_rotation": 0.0, "y": 0.0, "y_rotation": 0.0, "z": 0.0, "z_rotation": 0.0}, {"confidence": 0.0, "pointID": 21, "w_rotation": 1.0, "x": 0.0, "x_rotation": 0.0, "y": 0.0, "y_rotation": 0.0, "z": 0.0, "z_rotation": 0.0}, {"confidence": 0.0, "pointID": 22, "w_rotation": 1.0, "x": 0.0, "x_rotation": 0.0, "y": 0.0, "y_rotation": 0.0, "z": 0.0, "z_rotation": 0.0}, {"confidence": 0.0, "pointID": 23, "w_rotation": 1.0, "x": 0.0, "x_rotation": 0.0, "y": 0.0, "y_rotation": 0.0, "z": 0.0, "z_rotation": 0.0}]}]}