{"ID_Frame": 275, "People": [{"personID": 0, "skeleton": [{"confidence": 0.17873400449752808, "pointID": 0, "thingId": "org.eclipse.ditto:camera01", "w_rotation": 1.0, "x": -28.666000366210938, "x_rotation": 0.0, "y": 1.3779443502426147, "y_rotation": 0.0, "z": -1.4292223453521729, "z_rotation": 0.0}, {"confidence": 0.5102999806404114, "pointID": 1, "thingId": "org.eclipse.ditto:camera01", "w_rotation": 1.0, "x": -28.60300064086914, "x_rotation": 0.0, "y": 1.3046497106552124, "y_rotation": 0.0, "z": -1.505382776260376, "z_rotation": 0.0}, {"confidence": 0.4493350088596344, "pointID": 2, "thingId": "org.eclipse.ditto:camera01", "w_rotation": 1.0, "x": -28.519001007080078, "x_rotation": 0.0, "y": 1.3174599409103394, "y_rotation": 0.0, "z": -1.542921781539917, "z_rotation": 0.0}, {"confidence": 0.7067700028419495, "pointID": 3, "thingId": "org.eclipse.ditto:camera01", "w_rotation": 1.0, "x": -28.454999923706055, "x_rotation": 0.0, "y": 1.0885275602340698, "y_rotation": 0.0, "z": -1.608198881149292, "z_rotation": 0.0}, {"confidence": 0.7568539977073669, "pointID": 4, "thingId": "org.eclipse.ditto:camera01", "w_rotation": 1.0, "x": -28.43199920654297, "x_rotation": 0.0, "y": 0.8461898565292358, "y_rotation": 0.0, "z": -1.5862765312194824, "z_rotation": 0.0}, {"confidence": 0.4905639886856079, "pointID": 5, "thingId": "org.eclipse.ditto:camera01", "w_rotation": 1.0, "x": -28.81800079345703, "x_rotation": 0.0, "y": 1.308455228805542, "y_rotation": 0.0, "z": -1.478745937347412, "z_rotation": 0.0}, {"confidence": 0.0, "pointID": 6, "thingId": "org.eclipse.ditto:camera01", "w_rotation": 1.0, "x": 0.0, "x_rotation": 0.0, "y": 0.0, "y_rotation": 0.0, "z": 0.0, "z_rotation": 0.0}, {"confidence": 0.0, "pointID": 7, "thingId": "org.eclipse.ditto:camera01", "w_rotation": 1.0, "x": 0.0, "x_rotation": 0.0, "y": 0.0, "y_rotation": 0.0, "z": 0.0, "z_rotation": 0.0}, {"confidence": 0.3950670063495636, "pointID": 8, "thingId": "digitaltwin:Laboratorio_Corridoio:1", "w_rotation": 1.0, "x": -28.631000518798828, "x_rotation": 0.0, "y": 0.7897875308990479, "y_rotation": 0.0, "z": -1.5039482116699219, "z_rotation": 0.0}, {"confidence": 0.3089280128479004, "pointID": 9, "thingId": "org.eclipse.ditto:camera01", "w_rotation": 1.0, "x": -28.55500030517578, "x_rotation": 0.0, "y": 0.7892992496490479, "y_rotation": 0.0, "z": -1.5456082820892334, "z_rotation": 0.0}, {"confidence": 0.30166399478912354, "pointID": 10, "thingId": "org.eclipse.ditto:camera01", "w_rotation": 1.0, "x": -28.597000122070312, "x_rotation": 0.0, "y": 0.4388071596622467, "y_rotation": 0.0, "z": -1.6609265804290771, "z_rotation": 0.0}, {"confidence": 0.0, "pointID": 11, "thingId": "org.eclipse.ditto:camera01", "w_rotation": 1.0, "x": 0.0, "x_rotation": 0.0, "y": 0.0, "y_rotation": 0.0, "z": 0.0, "z_rotation": 0.0}, {"confidence": 0.41965800523757935, "pointID": 12, "thingId": "org.eclipse.ditto:camera01", "w_rotation": 1.0, "x": -28.75200080871582, "x_rotation": 0.0, "y": 0.777113676071167, "y_rotation": 0.0, "z": -1.4612994194030762, "z_rotation": 0.0}, {"confidence": 0.39012500643730164, "pointID": 13, "thingId": "org.eclipse.ditto:camera01", "w_rotation": 1.0, "x": -28.792999267578125, "x_rotation": 0.0, "y": 0.41568639874458313, "y_rotation": 0.0, "z": -1.4051942825317383, "z_rotation": 0.0}, {"confidence": 0.0, "pointID": 14, "thingId": "org.eclipse.ditto:camera01", "w_rotation": 1.0, "x": 0.0, "x_rotation": 0.0, "y": 0.0, "y_rotation": 0.0, "z": 0.0, "z_rotation": 0.0}, {"confidence": 0.0, "pointID": 15, "thingId": "org.eclipse.ditto:camera01", "w_rotation": 1.0, "x": 0.0, "x_rotation": 0.0, "y": 0.0, "y_rotation": 0.0, "z": 0.0, "z_rotation": 0.0}, {"confidence": 0.0, "pointID": 16, "thingId": "org.eclipse.ditto:camera01", "w_rotation": 1.0, "x": 0.0, "x_rotation": 0.0, "y": 0.0, "y_rotation": 0.0, "z": 0.0, "z_rotation": 0.0}, {"confidence": 0.0, "pointID": 17, "thingId": "org.eclipse.ditto:camera01", "w_rotation": 1.0, "x": 0.0, "x_rotation": 0.0, "y": 0.0, "y_rotation": 0.0, "z": 0.0, "z_rotation": 0.0}, {"confidence": 0.0, "pointID": 18, "thingId": "org.eclipse.ditto:camera01", "w_rotation": 1.0, "x": 0.0, "x_rotation": 0.0, "y": 0.0, "y_rotation": 0.0, "z": 0.0, "z_rotation": 0.0}, {"confidence": 0.0, "pointID": 19, "thingId": "org.eclipse.ditto:camera01", "w_rotation": 1.0, "x": 0.0, "x_rotation": 0.0, "y": 0.0, "y_rotation": 0.0, "z": 0.0, "z_rotation": 0.0}, {"confidence": 0.0, "pointID": 20, "thingId": "org.eclipse.ditto:camera01", "w_rotation": 1.0, "x": 0.0, "x_rotation": 0.0, "y": 0.0, "y_rotation": 0.0, "z": 0.0, "z_rotation": 0.0}, {"confidence": 0.0, "pointID": 21, "thingId": "org.eclipse.ditto:camera01", "w_rotation": 1.0, "x": 0.0, "x_rotation": 0.0, "y": 0.0, "y_rotation": 0.0, "z": 0.0, "z_rotation": 0.0}, {"confidence": 0.0, "pointID": 22, "thingId": "org.eclipse.ditto:camera01", "w_rotation": 1.0, "x": 0.0, "x_rotation": 0.0, "y": 0.0, "y_rotation": 0.0, "z": 0.0, "z_rotation": 0.0}, {"confidence": 0.0, "pointID": 23, "thingId": "org.eclipse.ditto:camera01", "w_rotation": 1.0, "x": 0.0, "x_rotation": 0.0, "y": 0.0, "y_rotation": 0.0, "z": 0.0, "z_rotation": 0.0}]}]}