{"ID_Frame": 60, "People": [{"personID": 0, "skeleton": [{"confidence": 0.0, "pointID": 0, "thingId": "org.eclipse.ditto:camera01", "w_rotation": 1.0, "x": 0.0, "x_rotation": 0.0, "y": 0.0, "y_rotation": 0.0, "z": 0.0, "z_rotation": 0.0}, {"confidence": 0.05552930012345314, "pointID": 1, "thingId": "org.eclipse.ditto:camera01", "w_rotation": 1.0, "x": -27.80500030517578, "x_rotation": 0.0, "y": 1.0088996887207031, "y_rotation": 0.0, "z": -1.066859245300293, "z_rotation": 0.0}, {"confidence": 0.14664900302886963, "pointID": 2, "thingId": "org.eclipse.ditto:camera01", "w_rotation": 1.0, "x": -27.825000762939453, "x_rotation": 0.0, "y": 0.989976167678833, "y_rotation": 0.0, "z": -1.1171762943267822, "z_rotation": 0.0}, {"confidence": 0.5942699909210205, "pointID": 3, "thingId": "org.eclipse.ditto:camera01", "w_rotation": 1.0, "x": -28.054000854492188, "x_rotation": 0.0, "y": 0.8605437278747559, "y_rotation": 0.0, "z": -1.1133389472961426, "z_rotation": 0.0}, {"confidence": 0.604112982749939, "pointID": 4, "thingId": "org.eclipse.ditto:camera01", "w_rotation": 1.0, "x": -28.082000732421875, "x_rotation": 0.0, "y": 0.644219160079956, "y_rotation": 0.0, "z": -1.058725357055664, "z_rotation": 0.0}, {"confidence": 0.0, "pointID": 5, "thingId": "org.eclipse.ditto:camera01", "w_rotation": 1.0, "x": 0.0, "x_rotation": 0.0, "y": 0.0, "y_rotation": 0.0, "z": 0.0, "z_rotation": 0.0}, {"confidence": 0.0, "pointID": 6, "thingId": "org.eclipse.ditto:camera01", "w_rotation": 1.0, "x": 0.0, "x_rotation": 0.0, "y": 0.0, "y_rotation": 0.0, "z": 0.0, "z_rotation": 0.0}, {"confidence": 0.0, "pointID": 7, "thingId": "org.eclipse.ditto:camera01", "w_rotation": 1.0, "x": 0.0, "x_rotation": 0.0, "y": 0.0, "y_rotation": 0.0, "z": 0.0, "z_rotation": 0.0}, {"confidence": 0.0, "pointID": 8, "thingId": "digitaltwin:Laboratorio_Corridoio:1", "w_rotation": 1.0, "x": 0.0, "x_rotation": 0.0, "y": 0.0, "y_rotation": 0.0, "z": 0.0, "z_rotation": 0.0}, {"confidence": 0.0, "pointID": 9, "thingId": "org.eclipse.ditto:camera01", "w_rotation": 1.0, "x": 0.0, "x_rotation": 0.0, "y": 0.0, "y_rotation": 0.0, "z": 0.0, "z_rotation": 0.0}, {"confidence": 0.0, "pointID": 10, "thingId": "org.eclipse.ditto:camera01", "w_rotation": 1.0, "x": 0.0, "x_rotation": 0.0, "y": 0.0, "y_rotation": 0.0, "z": 0.0, "z_rotation": 0.0}, {"confidence": 0.0, "pointID": 11, "thingId": "org.eclipse.ditto:camera01", "w_rotation": 1.0, "x": 0.0, "x_rotation": 0.0, "y": 0.0, "y_rotation": 0.0, "z": 0.0, "z_rotation": 0.0}, {"confidence": 0.0, "pointID": 12, "thingId": "org.eclipse.ditto:camera01", "w_rotation": 1.0, "x": 0.0, "x_rotation": 0.0, "y": 0.0, "y_rotation": 0.0, "z": 0.0, "z_rotation": 0.0}, {"confidence": 0.0, "pointID": 13, "thingId": "org.eclipse.ditto:camera01", "w_rotation": 1.0, "x": 0.0, "x_rotation": 0.0, "y": 0.0, "y_rotation": 0.0, "z": 0.0, "z_rotation": 0.0}, {"confidence": 0.0, "pointID": 14, "thingId": "org.eclipse.ditto:camera01", "w_rotation": 1.0, "x": 0.0, "x_rotation": 0.0, "y": 0.0, "y_rotation": 0.0, "z": 0.0, "z_rotation": 0.0}, {"confidence": 0.0, "pointID": 15, "thingId": "org.eclipse.ditto:camera01", "w_rotation": 1.0, "x": 0.0, "x_rotation": 0.0, "y": 0.0, "y_rotation": 0.0, "z": 0.0, "z_rotation": 0.0}, {"confidence": 0.0, "pointID": 16, "thingId": "org.eclipse.ditto:camera01", "w_rotation": 1.0, "x": 0.0, "x_rotation": 0.0, "y": 0.0, "y_rotation": 0.0, "z": 0.0, "z_rotation": 0.0}, {"confidence": 0.0, "pointID": 17, "thingId": "org.eclipse.ditto:camera01", "w_rotation": 1.0, "x": 0.0, "x_rotation": 0.0, "y": 0.0, "y_rotation": 0.0, "z": 0.0, "z_rotation": 0.0}, {"confidence": 0.0, "pointID": 18, "thingId": "org.eclipse.ditto:camera01", "w_rotation": 1.0, "x": 0.0, "x_rotation": 0.0, "y": 0.0, "y_rotation": 0.0, "z": 0.0, "z_rotation": 0.0}, {"confidence": 0.0, "pointID": 19, "thingId": "org.eclipse.ditto:camera01", "w_rotation": 1.0, "x": 0.0, "x_rotation": 0.0, "y": 0.0, "y_rotation": 0.0, "z": 0.0, "z_rotation": 0.0}, {"confidence": 0.0, "pointID": 20, "thingId": "org.eclipse.ditto:camera01", "w_rotation": 1.0, "x": 0.0, "x_rotation": 0.0, "y": 0.0, "y_rotation": 0.0, "z": 0.0, "z_rotation": 0.0}, {"confidence": 0.0, "pointID": 21, "thingId": "org.eclipse.ditto:camera01", "w_rotation": 1.0, "x": 0.0, "x_rotation": 0.0, "y": 0.0, "y_rotation": 0.0, "z": 0.0, "z_rotation": 0.0}, {"confidence": 0.0, "pointID": 22, "thingId": "org.eclipse.ditto:camera01", "w_rotation": 1.0, "x": 0.0, "x_rotation": 0.0, "y": 0.0, "y_rotation": 0.0, "z": 0.0, "z_rotation": 0.0}, {"confidence": 0.0, "pointID": 23, "thingId": "org.eclipse.ditto:camera01", "w_rotation": 1.0, "x": 0.0, "x_rotation": 0.0, "y": 0.0, "y_rotation": 0.0, "z": 0.0, "z_rotation": 0.0}]}]}