{"ID_Frame": 181, "People": [{"personID": 0, "skeleton": [{"confidence": 0.9215610027313232, "pointID": 0, "thingId": "org.eclipse.ditto:camera01", "w_rotation": 1.0, "x": -31.756000518798828, "x_rotation": 0.0, "y": 1.5088647603988647, "y_rotation": 0.0, "z": -0.7240538597106934, "z_rotation": 0.0}, {"confidence": 0.9497100114822388, "pointID": 1, "thingId": "org.eclipse.ditto:camera01", "w_rotation": 1.0, "x": -31.93600082397461, "x_rotation": 0.0, "y": 1.3068870306015015, "y_rotation": 0.0, "z": -0.710127592086792, "z_rotation": 0.0}, {"confidence": 0.9536169767379761, "pointID": 2, "thingId": "org.eclipse.ditto:camera01", "w_rotation": 1.0, "x": -31.999000549316406, "x_rotation": 0.0, "y": 1.3131498098373413, "y_rotation": 0.0, "z": -0.8196792602539062, "z_rotation": 0.0}, {"confidence": 0.9388359785079956, "pointID": 3, "thingId": "org.eclipse.ditto:camera01", "w_rotation": 1.0, "x": -32.20000076293945, "x_rotation": 0.0, "y": 1.0830870866775513, "y_rotation": 0.0, "z": -0.8636784553527832, "z_rotation": 0.0}, {"confidence": 0.9306269884109497, "pointID": 4, "thingId": "org.eclipse.ditto:camera01", "w_rotation": 1.0, "x": -32.41999816894531, "x_rotation": 0.0, "y": 0.840706467628479, "y_rotation": 0.0, "z": -0.9242815971374512, "z_rotation": 0.0}, {"confidence": 0.9244340062141418, "pointID": 5, "thingId": "org.eclipse.ditto:camera01", "w_rotation": 1.0, "x": -31.81399917602539, "x_rotation": 0.0, "y": 1.294758915901184, "y_rotation": 0.0, "z": -0.6115686893463135, "z_rotation": 0.0}, {"confidence": 0.8898950219154358, "pointID": 6, "thingId": "org.eclipse.ditto:camera01", "w_rotation": 1.0, "x": -31.81399917602539, "x_rotation": 0.0, "y": 1.042298436164856, "y_rotation": 0.0, "z": -0.5445280075073242, "z_rotation": 0.0}, {"confidence": 0.8781279921531677, "pointID": 7, "thingId": "org.eclipse.ditto:camera01", "w_rotation": 1.0, "x": -32.41999816894531, "x_rotation": 0.0, "y": 0.7648268938064575, "y_rotation": 0.0, "z": -0.39777278900146484, "z_rotation": 0.0}, {"confidence": 0.783752977848053, "pointID": 8, "thingId": "digitaltwin:Laboratorio_Corridoio:1", "w_rotation": 1.0, "x": -31.905000686645508, "x_rotation": 0.0, "y": 0.7810379266738892, "y_rotation": 0.0, "z": -0.7533783912658691, "z_rotation": 0.0}, {"confidence": 0.781387984752655, "pointID": 9, "thingId": "org.eclipse.ditto:camera01", "w_rotation": 1.0, "x": -32.03200149536133, "x_rotation": 0.0, "y": 0.7791193723678589, "y_rotation": 0.0, "z": -0.8110802173614502, "z_rotation": 0.0}, {"confidence": 0.8093780279159546, "pointID": 10, "thingId": "org.eclipse.ditto:camera01", "w_rotation": 1.0, "x": -31.727001190185547, "x_rotation": 0.0, "y": 0.4269619286060333, "y_rotation": 0.0, "z": -0.7765252590179443, "z_rotation": 0.0}, {"confidence": 0.8500810265541077, "pointID": 11, "thingId": "org.eclipse.ditto:camera01", "w_rotation": 1.0, "x": -32.30799865722656, "x_rotation": 0.0, "y": 0.0, "y_rotation": 0.0, "z": -0.6017115116119385, "z_rotation": 0.0}, {"confidence": 0.7637569904327393, "pointID": 12, "thingId": "org.eclipse.ditto:camera01", "w_rotation": 1.0, "x": -31.727001190185547, "x_rotation": 0.0, "y": 0.7764459848403931, "y_rotation": 0.0, "z": -0.699831485748291, "z_rotation": 0.0}, {"confidence": 0.8448989987373352, "pointID": 13, "thingId": "org.eclipse.ditto:camera01", "w_rotation": 1.0, "x": -31.78499984741211, "x_rotation": 0.0, "y": 0.3918602168560028, "y_rotation": 0.0, "z": -0.7930424213409424, "z_rotation": 0.0}, {"confidence": 0.7953370213508606, "pointID": 14, "thingId": "org.eclipse.ditto:camera01", "w_rotation": 1.0, "x": -31.64299964904785, "x_rotation": 0.0, "y": 0.0, "y_rotation": 0.0, "z": -0.8761026859283447, "z_rotation": 0.0}, {"confidence": 0.9194350242614746, "pointID": 15, "thingId": "org.eclipse.ditto:camera01", "w_rotation": 1.0, "x": -31.756000518798828, "x_rotation": 0.0, "y": 1.53085196018219, "y_rotation": 0.0, "z": -0.7405967712402344, "z_rotation": 0.0}, {"confidence": 0.916949987411499, "pointID": 16, "thingId": "org.eclipse.ditto:camera01", "w_rotation": 1.0, "x": -31.727001190185547, "x_rotation": 0.0, "y": 1.5190997123718262, "y_rotation": 0.0, "z": -0.6943531036376953, "z_rotation": 0.0}, {"confidence": 0.8430899977684021, "pointID": 17, "thingId": "org.eclipse.ditto:camera01", "w_rotation": 1.0, "x": -31.8439998626709, "x_rotation": 0.0, "y": 1.5145190954208374, "y_rotation": 0.0, "z": -0.7763059139251709, "z_rotation": 0.0}, {"confidence": 0.898231029510498, "pointID": 18, "thingId": "org.eclipse.ditto:camera01", "w_rotation": 1.0, "x": -31.756000518798828, "x_rotation": 0.0, "y": 1.4648903608322144, "y_rotation": 0.0, "z": -0.6689102649688721, "z_rotation": 0.0}, {"confidence": 0.6172609925270081, "pointID": 19, "thingId": "org.eclipse.ditto:camera01", "w_rotation": 1.0, "x": -31.999000549316406, "x_rotation": 0.0, "y": 0.0, "y_rotation": 0.0, "z": -0.9418525695800781, "z_rotation": 0.0}, {"confidence": 0.6496959924697876, "pointID": 20, "thingId": "org.eclipse.ditto:camera01", "w_rotation": 1.0, "x": -31.64299964904785, "x_rotation": 0.0, "y": 0.0, "y_rotation": 0.0, "z": -0.9083423614501953, "z_rotation": 0.0}, {"confidence": 0.7381380200386047, "pointID": 21, "thingId": "org.eclipse.ditto:camera01", "w_rotation": 1.0, "x": -31.671001434326172, "x_rotation": 0.0, "y": 0.0, "y_rotation": 0.0, "z": -0.8631362915039062, "z_rotation": 0.0}, {"confidence": 0.8320509791374207, "pointID": 22, "thingId": "org.eclipse.ditto:camera01", "w_rotation": 1.0, "x": -32.13100051879883, "x_rotation": 0.0, "y": 0.0, "y_rotation": 0.0, "z": -0.6890673637390137, "z_rotation": 0.0}, {"confidence": 0.8506069779396057, "pointID": 23, "thingId": "org.eclipse.ditto:camera01", "w_rotation": 1.0, "x": -32.16600036621094, "x_rotation": 0.0, "y": 0.0, "y_rotation": 0.0, "z": -0.6973402500152588, "z_rotation": 0.0}]}]}